nav_msgs/_dummy.cpython-313-x86_64-linux-gnu.so
ros_nav_msgs-5.5.1.data/data/include/nav_msgs/nav_msgs/msg/goals.h
ros_nav_msgs-5.5.1.data/data/include/nav_msgs/nav_msgs/msg/goals.hpp
ros_nav_msgs-5.5.1.data/data/include/nav_msgs/nav_msgs/msg/grid_cells.h
ros_nav_msgs-5.5.1.data/data/include/nav_msgs/nav_msgs/msg/grid_cells.hpp
ros_nav_msgs-5.5.1.data/data/include/nav_msgs/nav_msgs/msg/map_meta_data.h
ros_nav_msgs-5.5.1.data/data/include/nav_msgs/nav_msgs/msg/map_meta_data.hpp
ros_nav_msgs-5.5.1.data/data/include/nav_msgs/nav_msgs/msg/occupancy_grid.h
ros_nav_msgs-5.5.1.data/data/include/nav_msgs/nav_msgs/msg/occupancy_grid.hpp
ros_nav_msgs-5.5.1.data/data/include/nav_msgs/nav_msgs/msg/odometry.h
ros_nav_msgs-5.5.1.data/data/include/nav_msgs/nav_msgs/msg/odometry.hpp
ros_nav_msgs-5.5.1.data/data/include/nav_msgs/nav_msgs/msg/path.h
ros_nav_msgs-5.5.1.data/data/include/nav_msgs/nav_msgs/msg/path.hpp
ros_nav_msgs-5.5.1.data/data/include/nav_msgs/nav_msgs/msg/rosidl_generator_c__visibility_control.h
ros_nav_msgs-5.5.1.data/data/include/nav_msgs/nav_msgs/msg/rosidl_generator_cpp__visibility_control.hpp
ros_nav_msgs-5.5.1.data/data/include/nav_msgs/nav_msgs/msg/rosidl_typesupport_fastrtps_c__visibility_control.h
ros_nav_msgs-5.5.1.data/data/include/nav_msgs/nav_msgs/msg/rosidl_typesupport_fastrtps_cpp__visibility_control.h
ros_nav_msgs-5.5.1.data/data/include/nav_msgs/nav_msgs/msg/rosidl_typesupport_introspection_c__visibility_control.h
ros_nav_msgs-5.5.1.data/data/include/nav_msgs/nav_msgs/msg/detail/goals__builder.hpp
ros_nav_msgs-5.5.1.data/data/include/nav_msgs/nav_msgs/msg/detail/goals__description.c
ros_nav_msgs-5.5.1.data/data/include/nav_msgs/nav_msgs/msg/detail/goals__functions.c
ros_nav_msgs-5.5.1.data/data/include/nav_msgs/nav_msgs/msg/detail/goals__functions.h
ros_nav_msgs-5.5.1.data/data/include/nav_msgs/nav_msgs/msg/detail/goals__rosidl_typesupport_fastrtps_c.h
ros_nav_msgs-5.5.1.data/data/lib/python3.13/site-packages/nav_msgs-5.5.1-py3.13.egg-info/PKG-INFO
ros_nav_msgs-5.5.1.data/data/lib/python3.13/site-packages/nav_msgs-5.5.1-py3.13.egg-info/SOURCES.txt
ros_nav_msgs-5.5.1.data/data/lib/python3.13/site-packages/nav_msgs-5.5.1-py3.13.egg-info/dependency_links.txt
ros_nav_msgs-5.5.1.data/data/lib/python3.13/site-packages/nav_msgs-5.5.1-py3.13.egg-info/top_level.txt
ros_nav_msgs-5.5.1.dist-info/METADATA
ros_nav_msgs-5.5.1.dist-info/WHEEL
ros_nav_msgs-5.5.1.dist-info/top_level.txt
ros_nav_msgs-5.5.1.dist-info/RECORD
ros_nav_msgs-5.5.1.dist-info/licenses/LICENSE
