Metadata-Version: 2.4
Name: ros-nav-msgs
Version: 5.5.1
Summary: ROS nav_msgs package provides essential messages and services for robotic navigation, including maps, odometry, and path planning.
License-File: LICENSE
Requires-Dist: ros-std-msgs~=5.5.1
Requires-Dist: ros-geometry-msgs~=5.5.1
Requires-Dist: ros-builtin-interfaces~=2.3.0
Requires-Dist: ros-rosidl-default-runtime~=1.7.1
Dynamic: description
Dynamic: description-content-type
Dynamic: license-file
Dynamic: requires-dist
Dynamic: summary
